gcshelpers/__init__.py
gcshelpers/config.py
gcshelpers/exceptions.py
gcshelpers/logger.py
gcshelpers/storage.py
gcshelpers/telemetry.py
gcshelpers/assets/gcshelpers.conf.example
gcshelpers/assets/gcshelpers.conf.jsg
gcshelpers/assets/log.conf.example
gcshelpers_SaschaJust-0.1a1.dist-info/LICENSE
gcshelpers_SaschaJust-0.1a1.dist-info/METADATA
gcshelpers_SaschaJust-0.1a1.dist-info/WHEEL
gcshelpers_SaschaJust-0.1a1.dist-info/top_level.txt
gcshelpers_SaschaJust-0.1a1.dist-info/RECORD
