Metadata-Version: 2.1
Name: gcshelpers-SaschaJust
Version: 0.1a1
Summary: gcshelpers: a collection of helper classes and functions for the mozintermittent Google Cloud services.
Home-page: https://gitlab.com/mozintermittent/python-libraries/gcshelpers
Author: Sascha Just
Author-email: sascha.just@own-hero.net
License: MIT
Platform: UNKNOWN
Classifier: Programming Language :: Python :: 3
Classifier: License :: OSI Approved :: MIT License
Classifier: Operating System :: OS Independent
Requires-Python: >=3.6
Requires-Dist: google-cloud-pubsub
Requires-Dist: google-cloud-storage
Provides-Extra: develop
Requires-Dist: pylint ; extra == 'develop'
Requires-Dist: autopep8 ; extra == 'develop'
Requires-Dist: rope ; extra == 'develop'
Requires-Dist: notebook ; extra == 'develop'
Provides-Extra: dist
Requires-Dist: twine ; extra == 'dist'
Provides-Extra: docs
Requires-Dist: sphinx ; extra == 'docs'
Requires-Dist: recommonmark ; extra == 'docs'
Requires-Dist: sphinx-rtd-theme ; extra == 'docs'
Requires-Dist: doc8 ; extra == 'docs'
Requires-Dist: m2r ; extra == 'docs'
Provides-Extra: test
Requires-Dist: nose ; extra == 'test'
Requires-Dist: coverage ; extra == 'test'
